README.md
setup.cfg
setup.py
grim_gausbin_dist/Binomialdistribution.py
grim_gausbin_dist/Gaussiandistribution.py
grim_gausbin_dist/Generaldistribution.py
grim_gausbin_dist/__init__.py
grim_gausbin_dist.egg-info/PKG-INFO
grim_gausbin_dist.egg-info/SOURCES.txt
grim_gausbin_dist.egg-info/dependency_links.txt
grim_gausbin_dist.egg-info/not-zip-safe
grim_gausbin_dist.egg-info/top_level.txt